uringcore-0.9.1.dist-info/METADATA
uringcore-0.9.1.dist-info/WHEEL
uringcore-0.9.1.dist-info/licenses/LICENSE
uringcore/__init__.py
uringcore/_core.cpython-313-x86_64-linux-gnu.so
uringcore/datagram.py
uringcore/loop.py
uringcore/policy.py
uringcore/server.py
uringcore/ssl_transport.py
uringcore/subprocess.py
uringcore/transport.py
uringcore-0.9.1.dist-info/RECORD
