Metadata-Version: 2.4
Name: uringcore
Version: 0.9.1
Classifier: Development Status :: 4 - Beta
Classifier: Intended Audience :: Developers
Classifier: License :: OSI Approved :: Apache Software License
Classifier: Operating System :: POSIX :: Linux
Classifier: Programming Language :: Python :: 3
Classifier: Programming Language :: Python :: 3.10
Classifier: Programming Language :: Python :: 3.11
Classifier: Programming Language :: Python :: 3.12
Classifier: Programming Language :: Python :: 3.13
Classifier: Programming Language :: Rust
Classifier: Topic :: System :: Networking
Classifier: Topic :: Software Development :: Libraries :: Python Modules
Classifier: Framework :: AsyncIO
Classifier: Typing :: Typed
Requires-Dist: pytest>=7.0 ; extra == 'dev'
Requires-Dist: pytest-asyncio>=0.21 ; extra == 'dev'
Provides-Extra: dev
License-File: LICENSE
Summary: High-performance asyncio event loop for Python using io_uring - 36% faster than asyncio
Keywords: asyncio,io_uring,event-loop,uvloop,networking,high-performance,linux,rust
Author-email: Ankit Kumar Pandey <ankitkpandey1@gmail.com>
License: Apache-2.0
Requires-Python: >=3.10
Project-URL: Homepage, https://github.com/ankitkpandey1/uringcore
Project-URL: Repository, https://github.com/ankitkpandey1/uringcore
Project-URL: Documentation, https://github.com/ankitkpandey1/uringcore#readme
Project-URL: Changelog, https://github.com/ankitkpandey1/uringcore/releases
Project-URL: Bug Tracker, https://github.com/ankitkpandey1/uringcore/issues
